pysgf/__init__.py
pysgf/parser.py
pysgf-0.9.0.dist-info/LICENSE
pysgf-0.9.0.dist-info/METADATA
pysgf-0.9.0.dist-info/WHEEL
pysgf-0.9.0.dist-info/RECORD
